JiuyinweiMeishijianCaishenmeDounengBandao/README.md
JiuyinweiMeishijianCaishenmeDounengBandao/__init__.py
JiuyinweiMeishijianCaishenmeDounengBandao/__main__.py
JiuyinweiMeishijianCaishenmeDounengBandao/file.pdf
JiuyinweiMeishijianCaishenmeDounengBandao/index.html
jiuyinwei_meishijian_caishenme_douneng_bandao-2022.10.15.0.dist-info/METADATA
jiuyinwei_meishijian_caishenme_douneng_bandao-2022.10.15.0.dist-info/WHEEL
jiuyinwei_meishijian_caishenme_douneng_bandao-2022.10.15.0.dist-info/entry_points.txt
jiuyinwei_meishijian_caishenme_douneng_bandao-2022.10.15.0.dist-info/top_level.txt
jiuyinwei_meishijian_caishenme_douneng_bandao-2022.10.15.0.dist-info/RECORD
